cgdb/__init__.py
cgdb/cgdb.py
czechglobe/__init__.py
czechglobe/cgdb.py
czechglobe/client.py
czechglobe/cgdb/__init__.py
czechglobe/cgdb/client.py
cgdb_client-0.1.1.dist-info/METADATA
cgdb_client-0.1.1.dist-info/WHEEL
cgdb_client-0.1.1.dist-info/top_level.txt
cgdb_client-0.1.1.dist-info/RECORD
