Metadata-Version: 2.1
Name: cgdb-client
Version: 0.1.1
Summary: CGDB Client
Home-page: UNKNOWN
Author: CzechGlobe
Author-email: UNKNOWN
License: MIT
Platform: UNKNOWN
Requires-Dist: pandas (==1.1.5)
